django_zupit_logging/__init__.py
django_zupit_logging/apps.py
django_zupit_logging/logging.py
django_zupit_logging/settings.py
django_zupit_logging/migrations/__init__.py
tests/__init__.py
tests/test_settings.py
tests/urls.py
tests/views.py
tests/tests/__init__.py
tests/tests/test_logging.py
django_zupit_logging-0.2.4.dist-info/LICENSE
django_zupit_logging-0.2.4.dist-info/METADATA
django_zupit_logging-0.2.4.dist-info/WHEEL
django_zupit_logging-0.2.4.dist-info/top_level.txt
django_zupit_logging-0.2.4.dist-info/RECORD
