Metadata-Version: 2.1
Name: django-zupit-logging
Version: 0.2.4
Summary: A Django Middleware for logging requests and responses accordingly to Zupit Standards
Home-page: https://github.com/zupit-it/zupit-django/libs/django-zupit-logging
Author: Zupit SRL
Author-email: info@zupit.it
License: BSD-3-Clause
Classifier: Environment :: Web Environment
Classifier: Framework :: Django
Classifier: Intended Audience :: Developers
Classifier: License :: OSI Approved :: BSD License
Classifier: Operating System :: OS Independent
Classifier: Programming Language :: Python
Classifier: Programming Language :: Python :: 3
Classifier: Programming Language :: Python :: 3 :: Only
Classifier: Programming Language :: Python :: 3.6
Classifier: Programming Language :: Python :: 3.7
Classifier: Programming Language :: Python :: 3.8
Classifier: Topic :: Internet :: WWW/HTTP
Classifier: Topic :: Internet :: WWW/HTTP :: Dynamic Content
License-File: LICENSE
Requires-Dist: Django >=4.0
Requires-Dist: opencensus-ext-azure
